sanderthedragon/__init__.py
sanderthedragon/codeblockbuttons/__init__.py
sanderthedragon/codeblockbuttons/_static/clipboard.min.js
sanderthedragon/codeblockbuttons/_static/codeblock.css
sanderthedragon/codeblockbuttons/_static/codeblock.js
sanderthedragon/extralexers/__init__.py
sanderthedragon/inlinecodehighlight/__init__.py
sanderthedragon/mappedlinkrole/__init__.py
sanderthedragon_sphinxext-1.1.0.dist-info/METADATA
sanderthedragon_sphinxext-1.1.0.dist-info/WHEEL
sanderthedragon_sphinxext-1.1.0.dist-info/licenses/LICENSE
sanderthedragon_sphinxext-1.1.0.dist-info/RECORD
