Metadata-Version: 2.3
Name: sanderthedragon-sphinxext
Version: 1.1.0
Summary: SanderTheDragon's Sphinx Extensions
Project-URL: Homepage, https://sanderthedragon.gitlab.io/sphinx-extensions
Project-URL: Repository, https://gitlab.com/SanderTheDragon/sphinx-extensions
Project-URL: Issues, https://gitlab.com/SanderTheDragon/sphinx-extensions/issues
Project-URL: Changelog, https://sanderthedragon.gitlab.io/sphinx-extensions/changelog.html
Author-email: SanderTheDragon <sanderthedragon@zoho.com>
License-Expression: MIT
License-File: LICENSE
Classifier: Development Status :: 5 - Production/Stable
Classifier: Framework :: Sphinx :: Extension
Classifier: License :: OSI Approved :: MIT License
Classifier: Programming Language :: Python :: 3
Classifier: Programming Language :: Python :: 3.10
Classifier: Programming Language :: Python :: 3.11
Classifier: Programming Language :: Python :: 3.12
Classifier: Programming Language :: Python :: 3.13
Requires-Python: >=3.10
